geohash_py-0.1.3.dist-info/METADATA
geohash_py-0.1.3.dist-info/WHEEL
geohash_py-0.1.3.dist-info/license_files/LICENSE
geohash_py/__init__.py
geohash_py/geohash_py.cpython-39-aarch64-linux-gnu.so
geohash_py-0.1.3.dist-info/RECORD
