Metadata-Version: 2.3
Name: geohash-py
Version: 0.1.3
Classifier: Programming Language :: Rust
Classifier: Intended Audience :: Developers
Classifier: Operating System :: MacOS
Classifier: Operating System :: POSIX :: Linux
Classifier: Programming Language :: Python :: Implementation :: CPython
Classifier: Programming Language :: Python :: Implementation :: PyPy
Classifier: Typing :: Typed
License-File: LICENSE
Summary: Rust-powered library for geohashing, designed for high-performance spatial operations.
Author-email: Veli Eroglu <velieroglu@protonmail.com>
Requires-Python: >=3.8
